sksequitur/__init__.py
sksequitur/_core.cpython-38-darwin.so
sksequitur/api.py
sksequitur/core.py
scikit_sequitur-0.4.0.dist-info/METADATA
scikit_sequitur-0.4.0.dist-info/WHEEL
scikit_sequitur-0.4.0.dist-info/top_level.txt
scikit_sequitur-0.4.0.dist-info/RECORD
